{
	"tenantId": "ch.chandigarh",
	"moduleName": "egpm",
	"typeOfAdvertisement": [{
			"id": "10001",
			"code": "ADVERTISEMENT_OR_HOARDING_ON_WALL_OR_POST_OR_IN_THE_FORM_OF_NON-ILLUMINATED_SKY-SIGNS",
			"tenantId": "ch.chandigarh",
			"name": "Advertisement or hoarding on wall or post or in the form of non-illuminated sky-signs",
			"active": true,
			"duration": [
				"annual"
			],
			"subTypeOfAdvertisement": [{
					"id": "20001",
					"code": "NA",
					"typeOfAdvertisementId": "10001",
					"tenantId": "ch.chandigarh",
					"name": "NA",
					"active": true
				}
			],
			"durationDropdown": [{
				"id": "4",
				"code": "ANNUAL",
				"tenantId": "ch.chandigarh",
				"name": "Annual",
				"active": true
			}],
			"calculationType": "range"
		},
		{
			"id": "10002",
			"code": "ADVERTISEMENT_OR_HORDING_STANDING_BLANK_BUT_BEARING_THE_NAME_OF_THE_ADVERTISER_OR_WITH_THE_ANNOUNCEMENT_TO_BE_LET_DISPLAYED_THEREON",
			"tenantId": "ch.chandigarh",
			"name": "Advertisement or hoarding standing blank but bearing the name of the advertiser or with the announcement to be let displayed thereon",
			"active": true,
			"duration": [
				"annual"
			],
			"calculationType": "range",
			"subTypeOfAdvertisement": [{
					"id": "20004",
					"code": "NA",
					"typeOfAdvertisementId": "10002",
					"tenantId": "ch.chandigarh",
					"name": "NA",
					"active": true
				}
			],
			"durationDropdown": [{
				"id": "4",
				"code": "ANNUAL",
				"tenantId": "ch.chandigarh",
				"name": "Annual",
				"active": true
			}]
		},
		{
			"id": "10003",
			"code": "FIXED_ILLUMINATED_SKY-SIGNS_AND_ADVERTISEMENT",
			"tenantId": "ch.chandigarh",
			"name": "Fixed illuminated sky-signs and advertisement",
			"active": true,
			"duration": [
				"annual"
			],
			"calculationType": "range",
			"subTypeOfAdvertisement": [{
					"id": "20007",
					"code": "NA",
					"typeOfAdvertisementId": "10003",
					"tenantId": "ch.chandigarh",
					"name": "NA",
					"active": true
				}
			],
			"durationDropdown": [{
				"id": "4",
				"code": "ANNUAL",
				"tenantId": "ch.chandigarh",
				"name": "Annual",
				"active": true
			}]
		},
		{
			"id": "10004",
			"code": "DIGITAL_ADVERTISEMENT_NON-STATIC_LED_OR_SIMILAR_DEVICE_SINGLE_SIDE_RATES_WILL_BE_DOUBLE_TOP_THE_TRADITIONAL_AND_EXISTING_FIXED_ILLUMINATED_SKY-SIGNS",
			"tenantId": "ch.chandigarh",
			"name": "Digital Advertisement (non-static LED) or similar device single side rates will be double top the traditional and existing fixed illuminated sky-signs",
			"active": true,
			"duration": [
				"annual"
			],
			"calculationType": "range",
			"subTypeOfAdvertisement": [{
					"id": "20011",
					"code": "NA",
					"typeOfAdvertisementId": "10004",
					"tenantId": "ch.chandigarh",
					"name": "NA",
					"active": true
				}
			],
			"durationDropdown": [{
				"id": "4",
				"code": "ANNUAL",
				"tenantId": "ch.chandigarh",
				"name": "Annual",
				"active": true
			}]
		},
		{
			"id": "10005",
			"code": "NON-ILLUMINATED_ADVERTISEMENT_BOARDS_CARRIED_ON_VEHICLES_CABS_AUTO_RICKSHAW_PVT_VEHICLES_ETC_INCLUDING_BUSES",
			"tenantId": "ch.chandigarh",
			"name": "Non-illuminated advertisement boards carried on vehicles (i.e. cabs/auto rickshaw/Pvt. Vehicles etc.) including buses",
			"active": true,
			"duration": [
				"annual",
				"month"
			],
			"calculationType": "range",
			"subTypeOfAdvertisement": [{
					"id": "20015",
					"code": "NA",
					"typeOfAdvertisementId": "10005",
					"tenantId": "ch.chandigarh",
					"name": "NA",
					"active": true
				}
			],
			"durationDropdown": [{
					"id": "3",
					"code": "MONTHLY",
					"tenantId": "ch.chandigarh",
					"name": "Monthly",
					"active": true
				},
				{
					"id": "4",
					"code": "ANNUAL",
					"tenantId": "ch.chandigarh",
					"name": "Annual",
					"active": true
				}
			]
		},
		{
			"id": "10006",
			"code": "ILLUMINATED_ADVERTISEMENT_BOARDS_CARRIED_ON_VEHICLES_CABS_AUTO_RICKSHAW_PVT_VEHICLES_ETC_INCLUDING_BUSES_PLYING_CHANDIGARH",
			"tenantId": "ch.chandigarh",
			"name": "Illuminated advertisement boards carried on vehicles (i.e. cabs/auto, rickshaw/Pvt. Vehicles etc.) including buses plying chandigarh",
			"active": true,
			"duration": [
				"annual",
				"month"
			],
			"calculationType": "range",
			"subTypeOfAdvertisement": [{
					"id": "20017",
					"code": "NA",
					"typeOfAdvertisementId": "10006",
					"tenantId": "ch.chandigarh",
					"name": "NA",
					"active": true
				}
			],
			"durationDropdown": [{
					"id": "3",
					"code": "MONTHLY",
					"tenantId": "ch.chandigarh",
					"name": "Monthly",
					"active": true
				},
				{
					"id": "4",
					"code": "ANNUAL",
					"tenantId": "ch.chandigarh",
					"name": "Annual",
					"active": true
				}
			]
		},
		{
			"id": "10007",
			"code": "ADVERTISEMENT_BOARDS_ETC_CARRIED_BY_SANDWICH_BOARDMEN_NON-ILLUMINATED",
			"tenantId": "ch.chandigarh",
			"name": "Advertisement boards etc. carried by sandwich boardmen (Non-illuminated)",
			"active": true,
			"duration": [
				"annual",
				"month"
			],
			"calculationType": "range",
			"subTypeOfAdvertisement": [{
					"id": "20019",
					"code": "NA",
					"typeOfAdvertisementId": "10007",
					"tenantId": "ch.chandigarh",
					"name": "NA",
					"active": true
				}
			],
			"durationDropdown": [{
					"id": "3",
					"code": "MONTHLY",
					"tenantId": "ch.chandigarh",
					"name": "Monthly",
					"active": true
				},
				{
					"id": "4",
					"code": "ANNUAL",
					"tenantId": "ch.chandigarh",
					"name": "Annual",
					"active": true
				}
			]
		},
		{
			"id": "10008",
			"code": "ILLUMINATED_ADVERTISEMENT_BOARDS_ETC_CARRIED_BY_BOARDMEN_HANDCRAFT_CYCLIST_OR_CYCLE_RICKSHAWS",
			"tenantId": "ch.chandigarh",
			"name": "Illuminated advertisement boards etc. carried by boardmen, handcraft, cyclist or cycle rickshaws ",
			"active": true,
			"duration": [
				"annual",
				"month"
			],
			"calculationType": "range",
			"subTypeOfAdvertisement": [{
					"id": "20022",
					"code": "NA",
					"typeOfAdvertisementId": "10008",
					"tenantId": "ch.chandigarh",
					"name": "NA",
					"active": true
				}
			],
			"durationDropdown": [{
					"id": "3",
					"code": "MONTHLY",
					"tenantId": "ch.chandigarh",
					"name": "Monthly",
					"active": true
				},
				{
					"id": "4",
					"code": "ANNUAL",
					"tenantId": "ch.chandigarh",
					"name": "Annual",
					"active": true
				}
			]
		},
		{
			"id": "10009",
			"code": "FOR_ILLUMINATED_SKY-SIGNS_AND_ADVERTISEMENT_EXHIBITED_ON_SCREENS_BY_MEAN_OF_LANTERN_SLIDES_PROJECTOR_OR_SIMILAR_DEVICES",
			"tenantId": "ch.chandigarh",
			"name": "For illuminated sky-signs and advertisement exhibited on screens by mean of lantern slides, projector or similar devices",
			"active": true,
			"duration": [
				"annual",
				"month"
			],
			"calculationType": "range",
			"subTypeOfAdvertisement": [{
					"id": "20025",
					"code": "NA",
					"typeOfAdvertisementId": "10009",
					"tenantId": "ch.chandigarh",
					"name": "NA",
					"active": true
				}
			],
			"durationDropdown": [{
					"id": "3",
					"code": "MONTHLY",
					"tenantId": "ch.chandigarh",
					"name": "Monthly",
					"active": true
				},
				{
					"id": "4",
					"code": "ANNUAL",
					"tenantId": "ch.chandigarh",
					"name": "Annual",
					"active": true
				}
			]
		},
		{
			"id": "10010",
			"code": "PERMISSION_TO_AUCTIONEERS_TEMPORARY_TRAVELLING_SALES_ORGANIZER_EXHIBITOR_FAIR_ORGANIZERS_CIRCUSES_CONVENTION_ORGANIZER_ETC_TO_PUT_UP_NOT_MORE_THAN_TWO_HORDES_OF_REASONABLE_SIZE_LESS_THAN_5_SQ_FT_ADVERTISING_EACH_AUCTION_OR_SALE_OTHER_THAN_THOSE_ON_THE_PREMISES_WHERE_THE_AUCTION_IS_HELD_ONE_ON_A_PROMINENT_SITE_IN_THE_LOCALITY_AND_ONE_ON_THE_MUNICIPAL_LAMP_POST",
			"tenantId": "ch.chandigarh",
			"name": "Permission to auctioneers, temporary/ travelling sales organizer, exhibitor, fair organizers, circuses, convention organizer, etc. to put up not more than two hordes of reasonable size less than 5 sq. ft. advertising each auction or sale other than those on the premises where the auction is held. One on a prominent site in the locality and one on the municipal lamp post.",
			"active": true,
			"duration": [
				"day",
				"week"
			],
			"calculationType": "units",
			"subTypeOfAdvertisement": [
			{
				  "id": "20042",
				  "code":"NA",
				  "typeOfAdvertisementId":"10010",
				  "tenantId": "ch.chandigarh",
				  "name": "NA",
				  "active": true
			}
			],
			"durationDropdown": [{
					"id": "1",
					"code": "DAILY",
					"tenantId": "ch.chandigarh",
					"name": "Daily",
					"active": true
				},
				{
					"id": "2",
					"code": "WEEKLY",
					"tenantId": "ch.chandigarh",
					"name": "Weekly",
					"active": true
				}
			]
		},
		{
			"id": "10011",
			"code": "ADVT_BOARDS_AT_PERMITTED_LOCATIONS",
			"tenantId": "ch.chandigarh",
			"name": "Advt. boards at permitted locations",
			"active": false,
			"duration": [],
			"calculationType": "range",
			"subTypeOfAdvertisement": [{
					"id": "20028",
					"code": "NA",
					"typeOfAdvertisementId": "10011",
					"tenantId": "ch.chandigarh",
					"name": "NA",
					"active": true
				}
			],
			"durationDropdown": []
		},
		{
			"id": "10012",
			"code": "ADVT_EXHIBITED_IN_CINEMA_HOUSES_BY_MEANS_OF",
			"tenantId": "ch.chandigarh",
			"name": "Advt. exhibited in cinema houses by means of",
			"active": true,
			"duration": [
				"annual",
				"month"
			],
			"calculationType": "units",
			"subTypeOfAdvertisement": [{
					"id": "20030",
					"code": "LANTERN_SLIDES_OR_SIMILAR_DEVICES_PER_SCREEN_CAT12",
					"typeOfAdvertisementId": "10012",
					"tenantId": "ch.chandigarh",
					"name": "lantern slides or similar devices (per screen)",
					"active": true
				},
				{
					"id": "20031",
					"code": "THROUGH_SLIDE_PER_SCREEN_CAT12",
					"typeOfAdvertisementId": "10012",
					"tenantId": "ch.chandigarh",
					"name": "Through slide (per screen)",
					"active": true
				},
				{
					"id": "20032",
					"code": "THROUGH_REELS_COMPUTER_DEVICE_PROJECTOR_PER_SCREEN_CAT12",
					"typeOfAdvertisementId": "10012",
					"tenantId": "ch.chandigarh",
					"name": "Through reels/computer device/projector (per screen)",
					"active": true
				}
			],
			"durationDropdown": [{
					"id": "3",
					"code": "MONTHLY",
					"tenantId": "ch.chandigarh",
					"name": "Monthly",
					"active": true
				},
				{
					"id": "4",
					"code": "ANNUAL",
					"tenantId": "ch.chandigarh",
					"name": "Annual",
					"active": true
				}
			]
		},
		{
			"id": "10013",
			"code": "BANNERS_ON_BUILDINGS_OR_ON_OPEN_SPACE_OR_ROAD_SIDE_EXCEPT_MAIN_ROADS",
			"tenantId": "ch.chandigarh",
			"name": "Banners on buildings or on open space or road side, except main roads",
			"active": true,
			"duration": [
				"day"
			],
			"calculationType": "days",
			"subTypeOfAdvertisement": [{
					"id": "20033",
					"code": "NA",
					"typeOfAdvertisementId": "10013",
					"tenantId": "ch.chandigarh",
					"name": "NA",
					"active": true
				}
			],
			"durationDropdown": [{
				"id": "1",
				"code": "DAILY",
				"tenantId": "ch.chandigarh",
				"name": "Daily",
				"active": true
			}]
		},
		{
			"id": "10014",
			"code": "ADVT_BY_BALLOONS_MEASURED_ACROSS_THE_DIAMETER",
			"tenantId": "ch.chandigarh",
			"name": "Advt. by Balloons (Measured across the diameter)",
			"active": true,
			"duration": [
				"day"
			],
			"calculationType": "days",
			"subTypeOfAdvertisement": [{
					"id": "20035",
					"code": "NA",
					"typeOfAdvertisementId": "10014",
					"tenantId": "ch.chandigarh",
					"name": "NA",
					"active": true
				}
			],
			"durationDropdown": [{
				"id": "1",
				"code": "DAILY",
				"tenantId": "ch.chandigarh",
				"name": "Daily",
				"active": true
			}]
		},
		{
			"id": "10015",
			"code": "NON-ILLUMINATED_ADVT_BOARDS_CARRIED_ON_VEHICLES_SOLELY_AND_CHIEFLY_FOR_THE_PURPOSE_OF_ADVT_FOR_A_SPACE",
			"tenantId": "ch.chandigarh",
			"name": "Non-illuminated Advt. boards carried on vehicles solely and chiefly for the purpose of Advt. for a space ",
			"active": true,
			"duration": [
				"annual",
				"month"
			],
			"calculationType": "range",
			"subTypeOfAdvertisement": [{
					"id": "20037",
					"code": "NA",
					"typeOfAdvertisementId": "10015",
					"tenantId": "ch.chandigarh",
					"name": "NA",
					"active": true
				}
			],
			"durationDropdown": [{
					"id": "3",
					"code": "MONTHLY",
					"tenantId": "ch.chandigarh",
					"name": "Monthly",
					"active": true
				},
				{
					"id": "4",
					"code": "ANNUAL",
					"tenantId": "ch.chandigarh",
					"name": "Annual",
					"active": true
				}
			]
		},
		{
			"id": "10016",
			"code": "ILLUMINATED_ADVT_BOARDS_CARRIED_OUT_ON_VEHICLES_SOLELY_AND_CHIEFLY_FOR_THE_PURPOSE_OF_ADVT_FOR_A_SPACE",
			"tenantId": "ch.chandigarh",
			"name": "Illuminated Advt. boards carried out on vehicles solely and chiefly for the purpose of advt. for a space",
			"active": true,
			"duration": [
				"annual",
				"month"
			],
			"calculationType": "range",
			"subTypeOfAdvertisement": [{
					"id": "20039",
					"code": "NA",
					"typeOfAdvertisementId": "10016",
					"tenantId": "ch.chandigarh",
					"name": "NA",
					"active": true
				}
			],
			"durationDropdown": [{
					"id": "3",
					"code": "MONTHLY",
					"tenantId": "ch.chandigarh",
					"name": "Monthly",
					"active": true
				},
				{
					"id": "4",
					"code": "ANNUAL",
					"tenantId": "ch.chandigarh",
					"name": "Annual",
					"active": true
				}
			]
		}
	]
}